/*     */ package Model;
/*     */ 
/*     */ import Enum.Enum_Font_Ci;
/*     */ import Enum.Enum_Image_Ci;
/*     */ import Model.Dialog.Survey_List.Module_Option;
/*     */ import Model.Dialog.Survey_List.Module_Question;
/*     */ import Worker.ImageController;
/*     */ import java.awt.Color;
/*     */ import java.awt.Cursor;
/*     */ import java.awt.Dimension;
/*     */ import java.awt.GridBagConstraints;
/*     */ import java.awt.GridBagLayout;
/*     */ import java.awt.Insets;
/*     */ import java.awt.event.KeyEvent;
/*     */ import java.awt.event.KeyListener;
/*     */ import java.util.ArrayList;
/*     */ import java.util.List;
/*     */ import javax.swing.BorderFactory;
/*     */ import javax.swing.ButtonGroup;
/*     */ import javax.swing.ImageIcon;
/*     */ import javax.swing.JCheckBox;
/*     */ import javax.swing.JLabel;
/*     */ import javax.swing.JPanel;
/*     */ import javax.swing.JRadioButton;
/*     */ import javax.swing.JTextField;
/*     */ 
/*     */ 
/*     */ 
/*     */ 
/*     */ 
/*     */ 
/*     */ 
/*     */ 
/*     */ 
/*     */ 
/*     */ 
/*     */ 
/*     */ 
/*     */ 
/*     */ 
/*     */ 
/*     */ 
/*     */ 
/*     */ 
/*     */ 
/*     */ 
/*     */ 
/*     */ 
/*     */ 
/*     */ 
/*     */ 
/*     */ 
/*     */ 
/*     */ 
/*     */ 
/*     */ 
/*     */ 
/*     */ 
/*     */ 
/*     */ 
/*     */ 
/*     */ 
/*     */ 
/*     */ 
/*     */ 
/*     */ 
/*     */ 
/*     */ 
/*     */ 
/*     */ 
/*     */ 
/*     */ 
/*     */ 
/*     */ 
/*     */ 
/*     */ 
/*     */ 
/*     */ 
/*     */ 
/*     */ 
/*     */ 
/*     */ 
/*     */ 
/*     */ 
/*     */ 
/*     */ 
/*     */ 
/*     */ 
/*     */ 
/*     */ 
/*     */ 
/*     */ 
/*     */ 
/*     */ 
/*     */ 
/*     */ 
/*     */ 
/*     */ 
/*     */ 
/*     */ 
/*     */ 
/*     */ 
/*     */ 
/*     */ 
/*     */ 
/*     */ 
/*     */ 
/*     */ 
/*     */ 
/*     */ 
/*     */ 
/*     */ 
/*     */ 
/*     */ 
/*     */ 
/*     */ 
/*     */ 
/*     */ 
/*     */ 
/*     */ 
/*     */ 
/*     */ 
/*     */ 
/*     */ 
/*     */ 
/*     */ 
/*     */ 
/*     */ 
/*     */ 
/*     */ 
/*     */ 
/*     */ 
/*     */ 
/*     */ 
/*     */ 
/*     */ 
/*     */ 
/*     */ 
/*     */ 
/*     */ 
/*     */ 
/*     */ 
/*     */ 
/*     */ 
/*     */ 
/*     */ 
/*     */ 
/*     */ 
/*     */ 
/*     */ 
/*     */ 
/*     */ 
/*     */ 
/*     */ 
/*     */ 
/*     */ 
/*     */ 
/*     */ 
/*     */ 
/*     */ 
/*     */ 
/*     */ 
/*     */ 
/*     */ 
/*     */ 
/*     */ 
/*     */ 
/*     */ 
/*     */ 
/*     */ 
/*     */ 
/*     */ 
/*     */ 
/*     */ 
/*     */ 
/*     */ 
/*     */ 
/*     */ 
/*     */ 
/*     */ 
/*     */ 
/*     */ 
/*     */ 
/*     */ 
/*     */ 
/*     */ 
/*     */ 
/*     */ 
/*     */ 
/*     */ 
/*     */ 
/*     */ 
/*     */ 
/*     */ 
/*     */ 
/*     */ 
/*     */ 
/*     */ 
/*     */ 
/*     */ 
/*     */ 
/*     */ 
/*     */ 
/*     */ 
/*     */ 
/*     */ 
/*     */ 
/*     */ 
/*     */ 
/*     */ 
/*     */ 
/*     */ 
/*     */ 
/*     */ 
/*     */ 
/*     */ 
/*     */ 
/*     */ 
/*     */ 
/*     */ 
/*     */ 
/*     */ 
/*     */ 
/*     */ 
/*     */ 
/*     */ 
/*     */ 
/*     */ 
/*     */ 
/*     */ 
/*     */ 
/*     */ 
/*     */ 
/*     */ 
/*     */ 
/*     */ 
/*     */ 
/*     */ 
/*     */ 
/*     */ 
/*     */ 
/*     */ 
/*     */ 
/*     */ 
/*     */ 
/*     */ 
/*     */ 
/*     */ 
/*     */ 
/*     */ 
/*     */ 
/*     */ 
/*     */ 
/*     */ 
/*     */ 
/*     */ 
/*     */ 
/*     */ 
/*     */ 
/*     */ 
/*     */ 
/*     */ 
/*     */ 
/*     */ 
/*     */ 
/*     */ 
/*     */ 
/*     */ 
/*     */ 
/*     */ 
/*     */ 
/*     */ 
/*     */ 
/*     */ 
/*     */ 
/*     */ 
/*     */ 
/*     */ 
/*     */ 
/*     */ 
/*     */ 
/*     */ 
/*     */ 
/*     */ 
/*     */ 
/*     */ 
/*     */ 
/*     */ 
/*     */ 
/*     */ 
/*     */ 
/*     */ 
/*     */ 
/*     */ 
/*     */ 
/*     */ 
/*     */ 
/*     */ 
/*     */ 
/*     */ 
/*     */ 
/*     */ 
/*     */ 
/*     */ 
/*     */ 
/*     */ 
/*     */ 
/*     */ class Panel_Three
/*     */   extends JPanel
/*     */   implements KeyListener
/*     */ {
/* 312 */   private GridBagLayout gbl = new GridBagLayout();
/* 313 */   private GridBagConstraints gbc = new GridBagConstraints();
/*     */   
/*     */   private String type;
/* 316 */   private Module_Question md_qu = new Module_Question();
/*     */   
/* 318 */   private List<JTextField> list_tf = new ArrayList();
/* 319 */   private List<ArrayList<JRadioButton>> list_bt = new ArrayList();
/* 320 */   private List<ArrayList<JCheckBox>> list_cb = new ArrayList();
/*     */   
/*     */   public Panel_Three(String type, Module_Question md_qu) {
/* 323 */     this.type = type;
/* 324 */     this.md_qu = md_qu;
/*     */     
/* 326 */     setLayout(this.gbl);
/* 327 */     setOpaque(true);
/* 328 */     setBackground(Color.WHITE);
/*     */     
/* 330 */     createComponents();
/*     */   }
/*     */   
/*     */   public void createComponents() { String str;
/* 334 */     switch ((str = this.type).hashCode()) {case -2018804923:  if (str.equals("Linear")) {} break; case -768855440:  if (str.equals("OpenEnded")) break; break; case -368370607:  if (str.equals("DropDown")) {} break; case 175599017:  if (str.equals("CheckBoxGrid")) {} break; case 718473776:  if (str.equals("Multiple")) {} break; case 1033354689:  if (str.equals("RadioGrid")) {} break; case 1601505219:  if (!str.equals("CheckBox"))
/*     */       {
/* 336 */         return;JLabel label = new JLabel();
/* 337 */         label.setText("장문형 텍스트");
/* 338 */         label.setForeground(new Color(158, 158, 180));
/* 339 */         label.setPreferredSize(new Dimension(750, 60));
/* 340 */         label.setOpaque(false);
/* 341 */         label.setBorder(BorderFactory.createMatteBorder(0, 0, 2, 0, new Color(224, 224, 224)));
/* 342 */         label.setFont(Enum_Font_Ci.INFO.getFont());
/*     */         
/* 344 */         this.gbc.anchor = 11;
/* 345 */         this.gbc.fill = 1;
/*     */         
/* 347 */         this.gbc.gridx = 0;
/* 348 */         this.gbc.gridy = 0;
/* 349 */         this.gbc.gridwidth = 1;
/* 350 */         this.gbc.gridheight = 1;
/* 351 */         this.gbc.insets = new Insets(20, 0, 20, 0);
/* 352 */         add(label, this.gbc);
/* 353 */         return;
/*     */         
/*     */ 
/* 356 */         this.gbc.anchor = 11;
/* 357 */         this.gbc.fill = 1;
/* 358 */         this.gbc.gridx = 0;
/* 359 */         this.gbc.gridy = 0;
/* 360 */         this.gbc.gridwidth = 1;
/* 361 */         this.gbc.gridheight = 1;
/*     */         
/* 363 */         for (int i = 0; i < this.md_qu.getOption().size(); i++) {
/* 364 */           JLabel ll_num = new JLabel();
/* 365 */           ll_num.setText(i + 1 + ". ");
/* 366 */           ll_num.setFont(Enum_Font_Ci.INFO.getFont());
/* 367 */           ll_num.setPreferredSize(new Dimension(40, 40));
/*     */           
/* 369 */           JLabel ll_name = new JLabel();
/* 370 */           ll_name.setText(((Module_Option)this.md_qu.getOption().get(i)).getName());
/* 371 */           ll_name.setOpaque(false);
/* 372 */           ll_name.setBorder(BorderFactory.createMatteBorder(0, 0, 2, 0, new Color(224, 224, 224)));
/* 373 */           ll_name.setFont(Enum_Font_Ci.INFO.getFont());
/* 374 */           ll_name.setPreferredSize(new Dimension(600, 40));
/*     */           
/* 376 */           JTextField tf_point = new JTextField();
/* 377 */           tf_point.setText(String.valueOf(((Module_Option)this.md_qu.getOption().get(i)).getPoint()));
/* 378 */           tf_point.setFont(Enum_Font_Ci.INFO.getFont());
/* 379 */           tf_point.setHorizontalAlignment(0);
/* 380 */           tf_point.setPreferredSize(new Dimension(80, 40));
/* 381 */           tf_point.addKeyListener(this);
/*     */           
/* 383 */           this.gbc.insets = new Insets(20, 0, 20, 0);
/* 384 */           add(ll_num, this.gbc);
/* 385 */           this.gbc.gridx += 1;
/*     */           
/* 387 */           this.gbc.insets = new Insets(20, 0, 20, 20);
/* 388 */           add(ll_name, this.gbc);
/* 389 */           this.gbc.gridx += 1;
/*     */           
/* 391 */           this.gbc.insets = new Insets(20, 0, 20, 0);
/* 392 */           add(tf_point, this.gbc);
/*     */           
/* 394 */           this.gbc.gridx = 0;
/* 395 */           this.gbc.gridy += 1;
/*     */           
/* 397 */           this.list_tf.add(tf_point);
/*     */         }
/*     */       }
/*     */       else {
/* 401 */         this.gbc.anchor = 11;
/* 402 */         this.gbc.fill = 1;
/* 403 */         this.gbc.gridx = 0;
/* 404 */         this.gbc.gridy = 0;
/* 405 */         this.gbc.gridwidth = 1;
/* 406 */         this.gbc.gridheight = 1;
/*     */         
/* 408 */         for (int i = 0; i < this.md_qu.getOption().size(); i++) {
/* 409 */           JLabel ll_num = new JLabel();
/* 410 */           ll_num.setText(i + 1 + ". ");
/* 411 */           ll_num.setFont(Enum_Font_Ci.INFO.getFont());
/* 412 */           ll_num.setPreferredSize(new Dimension(40, 40));
/*     */           
/* 414 */           JLabel ll_name = new JLabel();
/* 415 */           ll_name.setText(((Module_Option)this.md_qu.getOption().get(i)).getName());
/* 416 */           ll_name.setOpaque(false);
/* 417 */           ll_name.setBorder(BorderFactory.createMatteBorder(0, 0, 2, 0, new Color(224, 224, 224)));
/* 418 */           ll_name.setFont(Enum_Font_Ci.INFO.getFont());
/* 419 */           ll_name.setPreferredSize(new Dimension(700, 40));
/*     */           
/* 421 */           this.gbc.insets = new Insets(20, 0, 20, 0);
/* 422 */           add(ll_num, this.gbc);
/* 423 */           this.gbc.gridx += 1;
/*     */           
/* 425 */           this.gbc.insets = new Insets(20, 0, 20, 20);
/* 426 */           add(ll_name, this.gbc);
/*     */           
/* 428 */           this.gbc.gridx = 0;
/* 429 */           this.gbc.gridy += 1;
/*     */         }
/* 431 */         return;
/*     */         
/* 433 */         this.gbc.anchor = 11;
/* 434 */         this.gbc.fill = 1;
/* 435 */         this.gbc.gridx = 0;
/* 436 */         this.gbc.gridy = 0;
/* 437 */         this.gbc.gridwidth = 1;
/* 438 */         this.gbc.gridheight = 1;
/*     */         
/* 440 */         for (int i = 0; i < this.md_qu.getOption().size(); i++) {
/* 441 */           JLabel ll_num = new JLabel();
/* 442 */           ll_num.setText(i + 1 + ". ");
/* 443 */           ll_num.setFont(Enum_Font_Ci.INFO.getFont());
/* 444 */           ll_num.setPreferredSize(new Dimension(40, 40));
/*     */           
/* 446 */           JLabel ll_name = new JLabel();
/* 447 */           ll_name.setText(((Module_Option)this.md_qu.getOption().get(i)).getName());
/* 448 */           ll_name.setOpaque(false);
/* 449 */           ll_name.setBorder(BorderFactory.createMatteBorder(0, 0, 2, 0, new Color(224, 224, 224)));
/* 450 */           ll_name.setFont(Enum_Font_Ci.INFO.getFont());
/* 451 */           ll_name.setPreferredSize(new Dimension(600, 40));
/*     */           
/* 453 */           JTextField tf_point = new JTextField();
/* 454 */           tf_point.setText(String.valueOf(((Module_Option)this.md_qu.getOption().get(i)).getPoint()));
/* 455 */           tf_point.setFont(Enum_Font_Ci.INFO.getFont());
/* 456 */           tf_point.setHorizontalAlignment(0);
/* 457 */           tf_point.setPreferredSize(new Dimension(80, 40));
/* 458 */           tf_point.addKeyListener(this);
/*     */           
/* 460 */           this.gbc.insets = new Insets(20, 0, 20, 0);
/* 461 */           add(ll_num, this.gbc);
/* 462 */           this.gbc.gridx += 1;
/*     */           
/* 464 */           this.gbc.insets = new Insets(20, 0, 20, 20);
/* 465 */           add(ll_name, this.gbc);
/* 466 */           this.gbc.gridx += 1;
/*     */           
/* 468 */           this.gbc.insets = new Insets(20, 0, 20, 0);
/* 469 */           add(tf_point, this.gbc);
/*     */           
/* 471 */           this.gbc.gridx = 0;
/* 472 */           this.gbc.gridy += 1;
/*     */           
/* 474 */           this.list_tf.add(tf_point);
/*     */         }
/* 476 */         return;
/*     */         
/* 478 */         this.gbc.anchor = 11;
/* 479 */         this.gbc.fill = 1;
/* 480 */         this.gbc.gridx = 0;
/* 481 */         this.gbc.gridy = 0;
/* 482 */         this.gbc.gridwidth = 1;
/* 483 */         this.gbc.gridheight = 1;
/*     */         
/* 485 */         for (int i = 0; i < this.md_qu.getOption().size(); i++) {
/* 486 */           JLabel ll_num = new JLabel();
/* 487 */           ll_num.setText(((Module_Option)this.md_qu.getOption().get(i)).getNumber());
/* 488 */           ll_num.setFont(Enum_Font_Ci.INFO.getFont());
/* 489 */           ll_num.setPreferredSize(new Dimension(40, 40));
/*     */           
/* 491 */           JLabel ll_name = new JLabel();
/* 492 */           ll_name.setText(((Module_Option)this.md_qu.getOption().get(i)).getName());
/* 493 */           ll_name.setOpaque(false);
/* 494 */           ll_name.setBorder(BorderFactory.createMatteBorder(0, 0, 2, 0, new Color(224, 224, 224)));
/* 495 */           ll_name.setFont(Enum_Font_Ci.INFO.getFont());
/* 496 */           ll_name.setPreferredSize(new Dimension(600, 40));
/*     */           
/* 498 */           this.gbc.insets = new Insets(20, 0, 20, 0);
/* 499 */           add(ll_num, this.gbc);
/* 500 */           this.gbc.gridx += 1;
/*     */           
/* 502 */           this.gbc.insets = new Insets(20, 0, 20, 20);
/* 503 */           add(ll_name, this.gbc);
/*     */           
/* 505 */           this.gbc.gridx = 0;
/* 506 */           this.gbc.gridy += 1;
/*     */         }
/* 508 */         return;
/*     */         
/* 510 */         List<String> lt_col = new ArrayList();
/* 511 */         List<String> lt_row = new ArrayList();
/*     */         
/* 513 */         for (int i = 0; i < this.md_qu.getOption().size(); i++) {
/* 514 */           if (((Module_Option)this.md_qu.getOption().get(i)).getNumber().contains("r")) {
/* 515 */             lt_row.add(((Module_Option)this.md_qu.getOption().get(i)).getName());
/* 516 */           } else if (((Module_Option)this.md_qu.getOption().get(i)).getNumber().contains("c")) {
/* 517 */             lt_col.add(((Module_Option)this.md_qu.getOption().get(i)).getName());
/*     */           }
/*     */         }
/*     */         
/* 521 */         this.gbc.anchor = 17;
/* 522 */         this.gbc.fill = 2;
/*     */         
/* 524 */         this.gbc.gridx = 0;
/* 525 */         this.gbc.gridy = 0;
/* 526 */         this.gbc.gridwidth = (lt_col.size() + 1);
/* 527 */         this.gbc.gridheight = 1;
/* 528 */         this.gbc.weightx = 1.0D;
/* 529 */         this.gbc.weighty = 1.0D;
/* 530 */         this.gbc.insets = new Insets(30, 30, 20, 30);
/* 531 */         add(new JLabel(), this.gbc);
/*     */         
/* 533 */         this.gbc.anchor = 10;
/* 534 */         this.gbc.fill = 0;
/*     */         
/* 536 */         this.gbc.gridx = 0;
/* 537 */         this.gbc.gridy = 1;
/* 538 */         this.gbc.gridwidth = 1;
/* 539 */         this.gbc.insets = new Insets(0, 30, 0, 0);
/*     */         
/* 541 */         add(new JLabel(), this.gbc);
/*     */         
/* 543 */         for (int i = 0; i < lt_col.size(); i++) {
/* 544 */           JLabel lbl = new JLabel((String)lt_col.get(i));
/* 545 */           lbl.setFont(Enum_Font_Ci.나눔바른고딕21.getFont());
/* 546 */           this.gbc.gridx = (i + 1);
/* 547 */           this.gbc.insets = new Insets(10, 10, 10, 10);
/*     */           
/* 549 */           add(lbl, this.gbc);
/*     */         }
/*     */         
/* 552 */         for (int i = 0; i < lt_row.size(); i++) {
/* 553 */           JLabel lbl = new JLabel((String)lt_row.get(i));
/* 554 */           lbl.setFont(Enum_Font_Ci.나눔바른고딕21.getFont());
/*     */           
/* 556 */           this.gbc.gridx = 0;
/* 557 */           this.gbc.gridy += 1;
/*     */           
/* 559 */           add(lbl, this.gbc);
/*     */           
/* 561 */           ButtonGroup group_G = new ButtonGroup();
/*     */           
/* 563 */           this.list_bt.add(new ArrayList());
/*     */           
/* 565 */           List<Integer> lt_target = ((Module_Option)this.md_qu.getOption().get(i)).getTarget();
/*     */           
/* 567 */           for (int j = 0; j < lt_col.size(); j++)
/*     */           {
/* 569 */             JRadioButton bt_radio = new JRadioButton();
/* 570 */             bt_radio.setIcon(new ImageIcon(
/* 571 */               ImageController.resizeImage(Enum_Image_Ci.BUTTON_RADIO_UNSELECTED.getImageIcon(), 28, 28)));
/* 572 */             bt_radio.setSelectedIcon(new ImageIcon(
/* 573 */               ImageController.resizeImage(Enum_Image_Ci.BUTTON_RADIO_SELECTED.getImageIcon(), 28, 28)));
/* 574 */             bt_radio.setCursor(new Cursor(12));
/* 575 */             bt_radio.setBackground(Color.WHITE);
/*     */             
/* 577 */             if (((Integer)lt_target.get(0)).intValue() == j)
/*     */             {
/* 579 */               bt_radio.setSelected(true);
/*     */             }
/*     */             
/* 582 */             group_G.add(bt_radio);
/*     */             
/* 584 */             this.gbc.gridx += 1;
/*     */             
/* 586 */             add(bt_radio, this.gbc);
/* 587 */             ((ArrayList)this.list_bt.get(i)).add(bt_radio);
/*     */           }
/*     */           
/* 590 */           this.gbc.gridx += 1;
/*     */           
/* 592 */           JTextField tf_point = new JTextField(String.valueOf(((Module_Option)this.md_qu.getOption().get(i)).getPoint()));
/* 593 */           tf_point.setFont(Enum_Font_Ci.INFO.getFont());
/* 594 */           tf_point.setHorizontalAlignment(0);
/* 595 */           tf_point.setPreferredSize(new Dimension(80, 40));
/* 596 */           add(tf_point, this.gbc);
/* 597 */           this.list_tf.add(tf_point);
/*     */         }
/*     */         
/* 600 */         this.gbc.gridy += 1;
/* 601 */         this.gbc.insets = new Insets(0, 0, 30, 0);
/* 602 */         add(new JLabel(), this.gbc);
/*     */         
/* 604 */         return;
/*     */         
/* 606 */         List<String> lt_col1 = new ArrayList();
/* 607 */         List<String> lt_row1 = new ArrayList();
/*     */         
/* 609 */         for (int i = 0; i < this.md_qu.getOption().size(); i++) {
/* 610 */           if (((Module_Option)this.md_qu.getOption().get(i)).getNumber().contains("r")) {
/* 611 */             lt_row1.add(((Module_Option)this.md_qu.getOption().get(i)).getName());
/* 612 */           } else if (((Module_Option)this.md_qu.getOption().get(i)).getNumber().contains("c")) {
/* 613 */             lt_col1.add(((Module_Option)this.md_qu.getOption().get(i)).getName());
/*     */           }
/*     */         }
/*     */         
/* 617 */         this.gbc.anchor = 17;
/* 618 */         this.gbc.fill = 2;
/*     */         
/* 620 */         this.gbc.gridx = 0;
/* 621 */         this.gbc.gridy = 0;
/* 622 */         this.gbc.gridwidth = (lt_col1.size() + 1);
/* 623 */         this.gbc.gridheight = 1;
/* 624 */         this.gbc.weightx = 1.0D;
/* 625 */         this.gbc.weighty = 1.0D;
/* 626 */         this.gbc.insets = new Insets(30, 30, 20, 30);
/* 627 */         add(new JLabel(), this.gbc);
/*     */         
/* 629 */         this.gbc.anchor = 10;
/* 630 */         this.gbc.fill = 0;
/*     */         
/* 632 */         this.gbc.gridx = 0;
/* 633 */         this.gbc.gridy = 1;
/* 634 */         this.gbc.gridwidth = 1;
/* 635 */         this.gbc.insets = new Insets(0, 30, 0, 0);
/*     */         
/* 637 */         add(new JLabel(), this.gbc);
/*     */         
/* 639 */         for (int i = 0; i < lt_col1.size(); i++) {
/* 640 */           JLabel lbl = new JLabel((String)lt_col1.get(i));
/* 641 */           lbl.setFont(Enum_Font_Ci.나눔바른고딕21.getFont());
/* 642 */           this.gbc.gridx = (i + 1);
/* 643 */           this.gbc.insets = new Insets(10, 10, 10, 10);
/*     */           
/* 645 */           add(lbl, this.gbc);
/*     */         }
/*     */         
/* 648 */         for (int i = 0; i < lt_row1.size(); i++)
/*     */         {
/* 650 */           JLabel lbl = new JLabel((String)lt_row1.get(i));
/* 651 */           lbl.setFont(Enum_Font_Ci.나눔바른고딕21.getFont());
/*     */           
/* 653 */           this.gbc.gridx = 0;
/* 654 */           this.gbc.gridy += 1;
/*     */           
/* 656 */           add(lbl, this.gbc);
/*     */           
/* 658 */           this.list_cb.add(new ArrayList());
/*     */           
/* 660 */           List<Integer> lt_target = ((Module_Option)this.md_qu.getOption().get(i)).getTarget();
/*     */           
/* 662 */           for (int j = 0; j < lt_col1.size(); j++)
/*     */           {
/* 664 */             JCheckBox bt_radio = new JCheckBox();
/* 665 */             bt_radio.setIcon(new ImageIcon(
/* 666 */               ImageController.resizeImage(Enum_Image_Ci.BUTTON_CHECKBOX_UNSELECTED.getImageIcon(), 28, 28)));
/* 667 */             bt_radio.setSelectedIcon(new ImageIcon(
/* 668 */               ImageController.resizeImage(Enum_Image_Ci.BUTTON_CHECKBOX_SELECTED.getImageIcon(), 28, 28)));
/* 669 */             bt_radio.setCursor(new Cursor(12));
/* 670 */             bt_radio.setBackground(Color.WHITE);
/*     */             
/* 672 */             if (lt_target.contains(Integer.valueOf(j)))
/*     */             {
/* 674 */               bt_radio.setSelected(true);
/*     */             }
/*     */             
/* 677 */             this.gbc.gridx += 1;
/*     */             
/* 679 */             add(bt_radio, this.gbc);
/* 680 */             ((ArrayList)this.list_cb.get(i)).add(bt_radio);
/*     */           }
/*     */           
/* 683 */           this.gbc.gridx += 1;
/*     */           
/* 685 */           JTextField tf_point = new JTextField(String.valueOf(((Module_Option)this.md_qu.getOption().get(i)).getPoint()));
/* 686 */           tf_point.setFont(Enum_Font_Ci.INFO.getFont());
/* 687 */           tf_point.setHorizontalAlignment(0);
/* 688 */           tf_point.setPreferredSize(new Dimension(80, 40));
/* 689 */           add(tf_point, this.gbc);
/* 690 */           this.list_tf.add(tf_point);
/*     */         }
/*     */         
/* 693 */         this.gbc.gridy += 1;
/* 694 */         this.gbc.insets = new Insets(0, 0, 30, 0);
/* 695 */         add(new JLabel(), this.gbc);
/*     */       }
/*     */       break;
/*     */     }
/*     */   }
/*     */   
/*     */   /* Error */
/*     */   public void savePoint(Module_Question mq)
/*     */   {
/*     */     // Byte code:
/*     */     //   0: aload_0
/*     */     //   1: getfield 53	Model/Panel_Three:type	Ljava/lang/String;
/*     */     //   4: dup
/*     */     //   5: astore_2
/*     */     //   6: invokevirtual 80	java/lang/String:hashCode	()I
/*     */     //   9: lookupswitch	default:+641->650, -2018804923:+67->76, -768855440:+79->88, -368370607:+91->100, 175599017:+103->112, 718473776:+115->124, 1033354689:+127->136, 1601505219:+139->148
/*     */     //   76: aload_2
/*     */     //   77: ldc 86
/*     */     //   79: invokevirtual 88	java/lang/String:equals	(Ljava/lang/Object;)Z
/*     */     //   82: ifne +568 -> 650
/*     */     //   85: goto +565 -> 650
/*     */     //   88: aload_2
/*     */     //   89: ldc 92
/*     */     //   91: invokevirtual 88	java/lang/String:equals	(Ljava/lang/Object;)Z
/*     */     //   94: ifne +556 -> 650
/*     */     //   97: goto +553 -> 650
/*     */     //   100: aload_2
/*     */     //   101: ldc 94
/*     */     //   103: invokevirtual 88	java/lang/String:equals	(Ljava/lang/Object;)Z
/*     */     //   106: ifne +116 -> 222
/*     */     //   109: goto +541 -> 650
/*     */     //   112: aload_2
/*     */     //   113: ldc 96
/*     */     //   115: invokevirtual 88	java/lang/String:equals	(Ljava/lang/Object;)Z
/*     */     //   118: ifne +351 -> 469
/*     */     //   121: goto +529 -> 650
/*     */     //   124: aload_2
/*     */     //   125: ldc 98
/*     */     //   127: invokevirtual 88	java/lang/String:equals	(Ljava/lang/Object;)Z
/*     */     //   130: ifne +30 -> 160
/*     */     //   133: goto +517 -> 650
/*     */     //   136: aload_2
/*     */     //   137: ldc 100
/*     */     //   139: invokevirtual 88	java/lang/String:equals	(Ljava/lang/Object;)Z
/*     */     //   142: ifne +142 -> 284
/*     */     //   145: goto +505 -> 650
/*     */     //   148: aload_2
/*     */     //   149: ldc 102
/*     */     //   151: invokevirtual 88	java/lang/String:equals	(Ljava/lang/Object;)Z
/*     */     //   154: ifne +496 -> 650
/*     */     //   157: goto +493 -> 650
/*     */     //   160: iconst_0
/*     */     //   161: istore_3
/*     */     //   162: goto +44 -> 206
/*     */     //   165: aload_1
/*     */     //   166: invokevirtual 203	Model/Dialog/Survey_List/Module_Question:getOption	()Ljava/util/List;
/*     */     //   169: iload_3
/*     */     //   170: invokeinterface 207 2 0
/*     */     //   175: checkcast 213	Model/Dialog/Survey_List/Module_Option
/*     */     //   178: aload_0
/*     */     //   179: getfield 47	Model/Panel_Three:list_tf	Ljava/util/List;
/*     */     //   182: iload_3
/*     */     //   183: invokeinterface 207 2 0
/*     */     //   188: checkcast 218	javax/swing/JTextField
/*     */     //   191: invokevirtual 368	javax/swing/JTextField:getText	()Ljava/lang/String;
/*     */     //   194: invokestatic 371	java/lang/Integer:valueOf	(Ljava/lang/String;)Ljava/lang/Integer;
/*     */     //   197: invokevirtual 313	java/lang/Integer:intValue	()I
/*     */     //   200: invokevirtual 374	Model/Dialog/Survey_List/Module_Option:setPoint	(I)V
/*     */     //   203: iinc 3 1
/*     */     //   206: iload_3
/*     */     //   207: aload_1
/*     */     //   208: invokevirtual 203	Model/Dialog/Survey_List/Module_Question:getOption	()Ljava/util/List;
/*     */     //   211: invokeinterface 237 1 0
/*     */     //   216: if_icmplt -51 -> 165
/*     */     //   219: goto +431 -> 650
/*     */     //   222: iconst_0
/*     */     //   223: istore_3
/*     */     //   224: goto +44 -> 268
/*     */     //   227: aload_1
/*     */     //   228: invokevirtual 203	Model/Dialog/Survey_List/Module_Question:getOption	()Ljava/util/List;
/*     */     //   231: iload_3
/*     */     //   232: invokeinterface 207 2 0
/*     */     //   237: checkcast 213	Model/Dialog/Survey_List/Module_Option
/*     */     //   240: aload_0
/*     */     //   241: getfield 47	Model/Panel_Three:list_tf	Ljava/util/List;
/*     */     //   244: iload_3
/*     */     //   245: invokeinterface 207 2 0
/*     */     //   250: checkcast 218	javax/swing/JTextField
/*     */     //   253: invokevirtual 368	javax/swing/JTextField:getText	()Ljava/lang/String;
/*     */     //   256: invokestatic 371	java/lang/Integer:valueOf	(Ljava/lang/String;)Ljava/lang/Integer;
/*     */     //   259: invokevirtual 313	java/lang/Integer:intValue	()I
/*     */     //   262: invokevirtual 374	Model/Dialog/Survey_List/Module_Option:setPoint	(I)V
/*     */     //   265: iinc 3 1
/*     */     //   268: iload_3
/*     */     //   269: aload_1
/*     */     //   270: invokevirtual 203	Model/Dialog/Survey_List/Module_Question:getOption	()Ljava/util/List;
/*     */     //   273: invokeinterface 237 1 0
/*     */     //   278: if_icmplt -51 -> 227
/*     */     //   281: goto +369 -> 650
/*     */     //   284: iconst_0
/*     */     //   285: istore_3
/*     */     //   286: iconst_0
/*     */     //   287: istore 4
/*     */     //   289: goto +163 -> 452
/*     */     //   292: aload_1
/*     */     //   293: invokevirtual 203	Model/Dialog/Survey_List/Module_Question:getOption	()Ljava/util/List;
/*     */     //   296: iload 4
/*     */     //   298: invokeinterface 207 2 0
/*     */     //   303: checkcast 213	Model/Dialog/Survey_List/Module_Option
/*     */     //   306: invokevirtual 240	Model/Dialog/Survey_List/Module_Option:getNumber	()Ljava/lang/String;
/*     */     //   309: ldc -13
/*     */     //   311: invokevirtual 245	java/lang/String:contains	(Ljava/lang/CharSequence;)Z
/*     */     //   314: ifeq +135 -> 449
/*     */     //   317: aload_1
/*     */     //   318: invokevirtual 203	Model/Dialog/Survey_List/Module_Question:getOption	()Ljava/util/List;
/*     */     //   321: iload 4
/*     */     //   323: invokeinterface 207 2 0
/*     */     //   328: checkcast 213	Model/Dialog/Survey_List/Module_Option
/*     */     //   331: aload_0
/*     */     //   332: getfield 47	Model/Panel_Three:list_tf	Ljava/util/List;
/*     */     //   335: iload_3
/*     */     //   336: invokeinterface 207 2 0
/*     */     //   341: checkcast 218	javax/swing/JTextField
/*     */     //   344: invokevirtual 368	javax/swing/JTextField:getText	()Ljava/lang/String;
/*     */     //   347: invokestatic 371	java/lang/Integer:valueOf	(Ljava/lang/String;)Ljava/lang/Integer;
/*     */     //   350: invokevirtual 313	java/lang/Integer:intValue	()I
/*     */     //   353: invokevirtual 374	Model/Dialog/Survey_List/Module_Option:setPoint	(I)V
/*     */     //   356: iconst_0
/*     */     //   357: istore 5
/*     */     //   359: goto +65 -> 424
/*     */     //   362: aload_0
/*     */     //   363: getfield 49	Model/Panel_Three:list_bt	Ljava/util/List;
/*     */     //   366: iload 4
/*     */     //   368: invokeinterface 207 2 0
/*     */     //   373: checkcast 44	java/util/ArrayList
/*     */     //   376: iload 5
/*     */     //   378: invokevirtual 377	java/util/ArrayList:get	(I)Ljava/lang/Object;
/*     */     //   381: checkcast 268	javax/swing/JRadioButton
/*     */     //   384: invokevirtual 378	javax/swing/JRadioButton:isSelected	()Z
/*     */     //   387: ifeq +34 -> 421
/*     */     //   390: aload_1
/*     */     //   391: invokevirtual 203	Model/Dialog/Survey_List/Module_Question:getOption	()Ljava/util/List;
/*     */     //   394: iload 4
/*     */     //   396: invokeinterface 207 2 0
/*     */     //   401: checkcast 213	Model/Dialog/Survey_List/Module_Option
/*     */     //   404: invokevirtual 265	Model/Dialog/Survey_List/Module_Option:getTarget	()Ljava/util/List;
/*     */     //   407: iload 5
/*     */     //   409: invokestatic 337	java/lang/Integer:valueOf	(I)Ljava/lang/Integer;
/*     */     //   412: invokeinterface 235 2 0
/*     */     //   417: pop
/*     */     //   418: goto +28 -> 446
/*     */     //   421: iinc 5 1
/*     */     //   424: iload 5
/*     */     //   426: aload_0
/*     */     //   427: getfield 49	Model/Panel_Three:list_bt	Ljava/util/List;
/*     */     //   430: iload 4
/*     */     //   432: invokeinterface 207 2 0
/*     */     //   437: checkcast 44	java/util/ArrayList
/*     */     //   440: invokevirtual 382	java/util/ArrayList:size	()I
/*     */     //   443: if_icmplt -81 -> 362
/*     */     //   446: iinc 3 1
/*     */     //   449: iinc 4 1
/*     */     //   452: iload 4
/*     */     //   454: aload_1
/*     */     //   455: invokevirtual 203	Model/Dialog/Survey_List/Module_Question:getOption	()Ljava/util/List;
/*     */     //   458: invokeinterface 237 1 0
/*     */     //   463: if_icmplt -171 -> 292
/*     */     //   466: goto +184 -> 650
/*     */     //   469: iconst_0
/*     */     //   470: istore 4
/*     */     //   472: iconst_0
/*     */     //   473: istore 5
/*     */     //   475: goto +161 -> 636
/*     */     //   478: aload_1
/*     */     //   479: invokevirtual 203	Model/Dialog/Survey_List/Module_Question:getOption	()Ljava/util/List;
/*     */     //   482: iload 5
/*     */     //   484: invokeinterface 207 2 0
/*     */     //   489: checkcast 213	Model/Dialog/Survey_List/Module_Option
/*     */     //   492: invokevirtual 240	Model/Dialog/Survey_List/Module_Option:getNumber	()Ljava/lang/String;
/*     */     //   495: ldc -13
/*     */     //   497: invokevirtual 245	java/lang/String:contains	(Ljava/lang/CharSequence;)Z
/*     */     //   500: ifeq +133 -> 633
/*     */     //   503: aload_1
/*     */     //   504: invokevirtual 203	Model/Dialog/Survey_List/Module_Question:getOption	()Ljava/util/List;
/*     */     //   507: iload 5
/*     */     //   509: invokeinterface 207 2 0
/*     */     //   514: checkcast 213	Model/Dialog/Survey_List/Module_Option
/*     */     //   517: aload_0
/*     */     //   518: getfield 47	Model/Panel_Three:list_tf	Ljava/util/List;
/*     */     //   521: iload 4
/*     */     //   523: invokeinterface 207 2 0
/*     */     //   528: checkcast 218	javax/swing/JTextField
/*     */     //   531: invokevirtual 368	javax/swing/JTextField:getText	()Ljava/lang/String;
/*     */     //   534: invokestatic 371	java/lang/Integer:valueOf	(Ljava/lang/String;)Ljava/lang/Integer;
/*     */     //   537: invokevirtual 313	java/lang/Integer:intValue	()I
/*     */     //   540: invokevirtual 374	Model/Dialog/Survey_List/Module_Option:setPoint	(I)V
/*     */     //   543: iconst_0
/*     */     //   544: istore 6
/*     */     //   546: goto +62 -> 608
/*     */     //   549: aload_0
/*     */     //   550: getfield 51	Model/Panel_Three:list_cb	Ljava/util/List;
/*     */     //   553: iload 5
/*     */     //   555: invokeinterface 207 2 0
/*     */     //   560: checkcast 44	java/util/ArrayList
/*     */     //   563: iload 6
/*     */     //   565: invokevirtual 377	java/util/ArrayList:get	(I)Ljava/lang/Object;
/*     */     //   568: checkcast 324	javax/swing/JCheckBox
/*     */     //   571: invokevirtual 383	javax/swing/JCheckBox:isSelected	()Z
/*     */     //   574: ifeq +31 -> 605
/*     */     //   577: aload_1
/*     */     //   578: invokevirtual 203	Model/Dialog/Survey_List/Module_Question:getOption	()Ljava/util/List;
/*     */     //   581: iload 5
/*     */     //   583: invokeinterface 207 2 0
/*     */     //   588: checkcast 213	Model/Dialog/Survey_List/Module_Option
/*     */     //   591: invokevirtual 265	Model/Dialog/Survey_List/Module_Option:getTarget	()Ljava/util/List;
/*     */     //   594: iload 6
/*     */     //   596: invokestatic 337	java/lang/Integer:valueOf	(I)Ljava/lang/Integer;
/*     */     //   599: invokeinterface 235 2 0
/*     */     //   604: pop
/*     */     //   605: iinc 6 1
/*     */     //   608: iload 6
/*     */     //   610: aload_0
/*     */     //   611: getfield 51	Model/Panel_Three:list_cb	Ljava/util/List;
/*     */     //   614: iload 5
/*     */     //   616: invokeinterface 207 2 0
/*     */     //   621: checkcast 44	java/util/ArrayList
/*     */     //   624: invokevirtual 382	java/util/ArrayList:size	()I
/*     */     //   627: if_icmplt -78 -> 549
/*     */     //   630: iinc 4 1
/*     */     //   633: iinc 5 1
/*     */     //   636: iload 5
/*     */     //   638: aload_1
/*     */     //   639: invokevirtual 203	Model/Dialog/Survey_List/Module_Question:getOption	()Ljava/util/List;
/*     */     //   642: invokeinterface 237 1 0
/*     */     //   647: if_icmplt -169 -> 478
/*     */     //   650: return
/*     */     // Line number table:
/*     */     //   Java source line #702	-> byte code offset #0
/*     */     //   Java source line #707	-> byte code offset #160
/*     */     //   Java source line #708	-> byte code offset #165
/*     */     //   Java source line #707	-> byte code offset #203
/*     */     //   Java source line #710	-> byte code offset #219
/*     */     //   Java source line #714	-> byte code offset #222
/*     */     //   Java source line #715	-> byte code offset #227
/*     */     //   Java source line #714	-> byte code offset #265
/*     */     //   Java source line #717	-> byte code offset #281
/*     */     //   Java source line #721	-> byte code offset #284
/*     */     //   Java source line #723	-> byte code offset #286
/*     */     //   Java source line #725	-> byte code offset #292
/*     */     //   Java source line #727	-> byte code offset #317
/*     */     //   Java source line #729	-> byte code offset #356
/*     */     //   Java source line #731	-> byte code offset #362
/*     */     //   Java source line #733	-> byte code offset #390
/*     */     //   Java source line #734	-> byte code offset #418
/*     */     //   Java source line #729	-> byte code offset #421
/*     */     //   Java source line #737	-> byte code offset #446
/*     */     //   Java source line #723	-> byte code offset #449
/*     */     //   Java source line #740	-> byte code offset #466
/*     */     //   Java source line #742	-> byte code offset #469
/*     */     //   Java source line #744	-> byte code offset #472
/*     */     //   Java source line #746	-> byte code offset #478
/*     */     //   Java source line #748	-> byte code offset #503
/*     */     //   Java source line #750	-> byte code offset #543
/*     */     //   Java source line #752	-> byte code offset #549
/*     */     //   Java source line #754	-> byte code offset #577
/*     */     //   Java source line #750	-> byte code offset #605
/*     */     //   Java source line #757	-> byte code offset #630
/*     */     //   Java source line #744	-> byte code offset #633
/*     */     //   Java source line #762	-> byte code offset #650
/*     */     // Local variable table:
/*     */     //   start	length	slot	name	signature
/*     */     //   0	651	0	this	Panel_Three
/*     */     //   0	651	1	mq	Module_Question
/*     */     //   5	144	2	str	String
/*     */     //   161	46	3	i	int
/*     */     //   223	46	3	i	int
/*     */     //   285	162	3	count	int
/*     */     //   287	166	4	i	int
/*     */     //   470	161	4	count1	int
/*     */     //   357	68	5	j	int
/*     */     //   473	164	5	i	int
/*     */     //   544	65	6	j	int
/*     */   }
/*     */   
/*     */   public void setBord(Color color)
/*     */   {
/* 765 */     setBorder(BorderFactory.createMatteBorder(0, 2, 2, 2, color));
/*     */   }
/*     */   
/*     */ 
/*     */ 
/*     */ 
/*     */   public void keyPressed(KeyEvent arg0) {}
/*     */   
/*     */ 
/*     */ 
/*     */ 
/*     */   public void keyReleased(KeyEvent arg0) {}
/*     */   
/*     */ 
/*     */ 
/*     */ 
/*     */   public void keyTyped(KeyEvent arg0)
/*     */   {
/* 783 */     char c = arg0.getKeyChar();
/* 784 */     JTextField tf = (JTextField)arg0.getSource();
/*     */     
/* 786 */     if ((!Character.isDigit(c)) || (tf.getText().length() > 2)) {
/* 787 */       arg0.consume();
/* 788 */       return;
/*     */     }
/*     */   }
/*     */ }


/* Location:              C:\Users\Owner\Desktop\정다운마을 서버프로그램\!\Model\Panel_Three.class
 * Java compiler version: 8 (52.0)
 * JD-Core Version:       0.7.1
 */